dictation_to_shell/__init__.py
dictation_to_shell/main.py
dictation_to_shell-0.1.1.dist-info/WHEEL
dictation_to_shell-0.1.1.dist-info/entry_points.txt
dictation_to_shell-0.1.1.dist-info/METADATA
dictation_to_shell-0.1.1.dist-info/RECORD
